MANIFEST.in
README.md
setup.cfg
setup.py
xiongxiong/__init__.py
xiongxiong/xiongxiong.py
xiongxiong.egg-info/PKG-INFO
xiongxiong.egg-info/SOURCES.txt
xiongxiong.egg-info/dependency_links.txt
xiongxiong.egg-info/top_level.txt